optimflow_lifex/__init__.py
optimflow_lifex/lifex.py
optimflow_lifex/lifex_params.py
optimflow_lifex-0.0.2.dist-info/licenses/LICENSE
optimflow_lifex-0.0.2.dist-info/METADATA
optimflow_lifex-0.0.2.dist-info/WHEEL
optimflow_lifex-0.0.2.dist-info/top_level.txt
optimflow_lifex-0.0.2.dist-info/RECORD
