Metadata-Version: 2.4
Name: optimflow-lifex
Version: 0.0.2
Requires-Python: >=3.9
License-File: LICENSE
Requires-Dist: pyrameters
Requires-Dist: optimflow
Dynamic: license-file
